MANIFEST.in
README.rst
setup.py
housecanary/__init__.py
housecanary/apiclient.py
housecanary/authentication.py
housecanary/constants.py
housecanary/exceptions.py
housecanary/object.py
housecanary/output.py
housecanary/requestclient.py
housecanary/response.py
housecanary/utilities.py
housecanary.egg-info/PKG-INFO
housecanary.egg-info/SOURCES.txt
housecanary.egg-info/dependency_links.txt
housecanary.egg-info/entry_points.txt
housecanary.egg-info/not-zip-safe
housecanary.egg-info/requires.txt
housecanary.egg-info/top_level.txt
housecanary/excel/__init__.py
housecanary/excel/analytics_data_excel.py
housecanary/excel/utilities.py
housecanary/hc_api_excel_concat/__init__.py
housecanary/hc_api_excel_concat/hc_api_excel_concat.py
housecanary/hc_api_export/__init__.py
housecanary/hc_api_export/hc_api_export.py