Metadata-Version: 1.1
Name: housecanary
Version: 0.7.0
Summary: Client Wrapper for the HouseCanary API
Home-page: http://github.com/housecanary/hc-api-python
Author: HouseCanary
Author-email: techops@housecanary.com
License: MIT
Platform: UNKNOWN
Classifier: Programming Language :: Python :: 2.7
Classifier: Programming Language :: Python :: 3.5
Classifier: Programming Language :: Python :: 3.6
